pyramid_marshmallow/__init__.py
pyramid_marshmallow/openapi/__init__.py
pyramid_marshmallow/openapi/generate.py
pyramid_marshmallow/openapi/serve.py
pyramid_marshmallow/openapi/spec.py
pyramid_marshmallow-0.8.0.dist-info/METADATA
pyramid_marshmallow-0.8.0.dist-info/WHEEL
pyramid_marshmallow-0.8.0.dist-info/entry_points.txt
pyramid_marshmallow-0.8.0.dist-info/top_level.txt
pyramid_marshmallow-0.8.0.dist-info/RECORD
