Metadata-Version: 2.1
Name: pyramid-marshmallow
Version: 0.8.0
Summary: Validate request and response data with Marshmallow and optionally generate an OpenAPI spec.
Home-page: https://github.com/luhn/pyramid-marshmallow
Author: Theron Luhn
Author-email: theron@luhn.com
Classifier: Development Status :: 3 - Alpha
Classifier: Framework :: Pyramid
Classifier: Intended Audience :: Developers
Classifier: License :: OSI Approved :: MIT License
Classifier: Operating System :: OS Independent
Classifier: Programming Language :: Python :: 3 :: Only
Classifier: Programming Language :: Python :: 3
Classifier: Programming Language :: Python :: 3.8
Classifier: Programming Language :: Python :: 3.9
Classifier: Programming Language :: Python :: 3.10
Classifier: Programming Language :: Python :: 3.11
Classifier: Programming Language :: Python :: 3.12
Classifier: Programming Language :: Python :: Implementation :: CPython
Classifier: Programming Language :: Python :: Implementation :: PyPy
Classifier: Programming Language :: Python
Requires-Python: >=3.7
Requires-Dist: pyramid>=1.7
Requires-Dist: marshmallow~=3.0
Requires-Dist: zope.interface>=3.8.0
Provides-Extra: openapi
Requires-Dist: apispec<7,>=3.0; extra == "openapi"
Requires-Dist: PyYAML<7,>=5.4; extra == "openapi"
Provides-Extra: testing
Requires-Dist: pytest~=6.2; extra == "testing"
Requires-Dist: webtest~=2.0; extra == "testing"
Provides-Extra: linting
Requires-Dist: ruff~=0.7.0; extra == "linting"
